lorem_text/__init__.py
lorem_text/cli.py
lorem_text/lorem.py
lorem_text-2.1.dist-info/AUTHORS.rst
lorem_text-2.1.dist-info/LICENSE
lorem_text-2.1.dist-info/METADATA
lorem_text-2.1.dist-info/WHEEL
lorem_text-2.1.dist-info/entry_points.txt
lorem_text-2.1.dist-info/top_level.txt
lorem_text-2.1.dist-info/RECORD
