Metadata-Version: 2.1
Name: lorem_text
Version: 2.1
Summary: Dummy lorem ipsum text generator 
Home-page: https://github.com/TheAbhijeet/lorem_text
Author: Abhijeet Pal
License: MIT license
Keywords: lorem_text
Platform: UNKNOWN
Classifier: Development Status :: 5 - Production/Stable
Classifier: Intended Audience :: Developers
Classifier: License :: OSI Approved :: MIT License
Classifier: Natural Language :: English
Classifier: Programming Language :: Python :: 3
Classifier: Programming Language :: Python :: 3.5
Classifier: Programming Language :: Python :: 3.6
Classifier: Programming Language :: Python :: 3.7
Classifier: Programming Language :: Python :: 3.8
Classifier: Programming Language :: Python :: 3.9
Classifier: Programming Language :: Python :: 3.10
Requires-Python: >=3.5
License-File: LICENSE
License-File: AUTHORS.rst
